[
  {
    "full_name": "actions/github-script",
    "stargazers_count": 724,
    "open_issues_count": 4,
    "forks_count": 82
  },
  {
    "full_name": "bdougie/git-twitch",
    "stargazers_count": 9,
    "open_issues_count": 0,
    "forks_count": 2
  },
  {
    "full_name": "open-sauced/swag",
    "stargazers_count": 4,
    "open_issues_count": 1,
    "forks_count": 1
  },
  {
    "full_name": "nodejs/node",
    "stargazers_count": 75219,
    "open_issues_count": 1248,
    "forks_count": 18747
  },
  {
    "full_name": "actions/first-interaction",
    "stargazers_count": 80,
    "open_issues_count": 19,
    "forks_count": 40
  },
  {
    "full_name": "tc39/test262",
    "stargazers_count": 1536,
    "open_issues_count": 103,
    "forks_count": 349
  },
  {
    "full_name": "30-seconds/30-seconds-of-code",
    "stargazers_count": 65973,
    "open_issues_count": 1,
    "forks_count": 7293
  },
  {
    "full_name": "pizzaql/pizzaql",
    "stargazers_count": 616,
    "open_issues_count": 0,
    "forks_count": 58
  },
  {
    "full_name": "spf13/cobra",
    "stargazers_count": 19571,
    "open_issues_count": 277,
    "forks_count": 1654
  },
  {
    "full_name": "gatsbyjs/gatsby",
    "stargazers_count": 48092,
    "open_issues_count": 564,
    "forks_count": 9101
  },
  {
    "full_name": "torvalds/linux",
    "stargazers_count": 101814,
    "open_issues_count": 324,
    "forks_count": 34652
  },
  {
    "full_name": "cli/cli",
    "stargazers_count": 20333,
    "open_issues_count": 327,
    "forks_count": 1635
  },
  {
    "full_name": "MichaelJolley/vulcan",
    "stargazers_count": 22,
    "open_issues_count": 7,
    "forks_count": 12
  },
  {
    "full_name": "release-drafter/release-drafter",
    "stargazers_count": 1513,
    "open_issues_count": 90,
    "forks_count": 156
  },
  {
    "full_name": "open-sauced/open-sauced",
    "stargazers_count": 312,
    "open_issues_count": 31,
    "forks_count": 90
  },
  {
    "full_name": "bdougie/live",
    "stargazers_count": 4,
    "open_issues_count": 15,
    "forks_count": 4
  },
  {
    "full_name": "forem/forem",
    "stargazers_count": 15605,
    "open_issues_count": 911,
    "forks_count": 2653
  },
  {
    "full_name": "graphql/graphiql",
    "stargazers_count": 11476,
    "open_issues_count": 176,
    "forks_count": 1207
  },
  {
    "full_name": "bdougie/open-sauced",
    "stargazers_count": 0,
    "open_issues_count": 0,
    "forks_count": 0
  },
  {
    "full_name": "OneGraph/onegraph-client",
    "stargazers_count": 18,
    "open_issues_count": 16,
    "forks_count": 6
  },
  {
    "full_name": "nock/nock",
    "stargazers_count": 10123,
    "open_issues_count": 44,
    "forks_count": 706
  },
  {
    "full_name": "JustinBeckwith/linkinator",
    "stargazers_count": 497,
    "open_issues_count": 21,
    "forks_count": 28
  },
  {
    "full_name": "primer/components",
    "stargazers_count": 1005,
    "open_issues_count": 44,
    "forks_count": 137
  },
  {
    "full_name": "babel/babel",
    "stargazers_count": 37930,
    "open_issues_count": 835,
    "forks_count": 4599
  }
]